ninfs/__init__.py
ninfs/__main__.py
ninfs/_gui.py
ninfs/_pyi_main.py
ninfs/fmt_detect.py
ninfs/fuse.py
ninfs/main.py
ninfs/reg_shell.py
ninfs/data/1024x1024.png
ninfs/data/128x128.png
ninfs/data/16x16.png
ninfs/data/32x32.png
ninfs/data/64x64.png
ninfs/data/windows.ico
ninfs/hac/__init__.py
ninfs/hac/_crypto.cp37-win32.pyd
ninfs/hac/crypto.py
ninfs/hac/libcrypto-1_1.dll
ninfs/hac/openssl-license.txt
ninfs/mount/__init__.py
ninfs/mount/_common.py
ninfs/mount/cci.py
ninfs/mount/cdn.py
ninfs/mount/cia.py
ninfs/mount/exefs.py
ninfs/mount/nandctr.py
ninfs/mount/nandhac.py
ninfs/mount/nandtwl.py
ninfs/mount/ncch.py
ninfs/mount/romfs.py
ninfs/mount/sd.py
ninfs/mount/srl.py
ninfs/mount/threedsx.py
ninfs/mount/titledir.py
ninfs/pyctr/__init__.py
ninfs/pyctr/common.py
ninfs/pyctr/crypto.py
ninfs/pyctr/util.py
ninfs/pyctr/types/__init__.py
ninfs/pyctr/types/exefs.py
ninfs/pyctr/types/ncch.py
ninfs/pyctr/types/romfs.py
ninfs/pyctr/types/smdh.py
ninfs/pyctr/types/tmd.py
ninfs-1.6.1.dist-info/LICENSE.md
ninfs-1.6.1.dist-info/METADATA
ninfs-1.6.1.dist-info/WHEEL
ninfs-1.6.1.dist-info/entry_points.txt
ninfs-1.6.1.dist-info/top_level.txt
ninfs-1.6.1.dist-info/RECORD
