Metadata-Version: 2.1
Name: ninfs
Version: 1.6.1
Summary: FUSE filesystem Python scripts for Nintendo console files
Home-page: https://github.com/ihaveamac/ninfs
Author: Ian Burgwin
Author-email: ian@ianburgwin.net
License: MIT
Platform: UNKNOWN
Classifier: Topic :: Utilities
Classifier: License :: OSI Approved :: MIT License
Classifier: Programming Language :: Python :: 3
Classifier: Programming Language :: Python :: 3.6
Classifier: Programming Language :: Python :: 3.7
Provides-Extra: gui
